dqm_ml_images/__init__.py
dqm_ml_images/_version_.py
dqm_ml_images/py.typed
dqm_ml_images/visual_features.py
dqm_ml_images-1.1.4.dist-info/METADATA
dqm_ml_images-1.1.4.dist-info/WHEEL
dqm_ml_images-1.1.4.dist-info/entry_points.txt
dqm_ml_images-1.1.4.dist-info/top_level.txt
dqm_ml_images-1.1.4.dist-info/RECORD
